repartee/__init__.py
repartee/cli.py
repartee/config.py
repartee/output_formatter.py
repartee/prompt_handler.py
repartee/repl.py
repartee/spending_tracker.py
repartee/api_clients/__init__.py
repartee/api_clients/openai.py
repartee-0.1.1.dist-info/LICENSE
repartee-0.1.1.dist-info/METADATA
repartee-0.1.1.dist-info/WHEEL
repartee-0.1.1.dist-info/entry_points.txt
repartee-0.1.1.dist-info/top_level.txt
repartee-0.1.1.dist-info/RECORD
