Metadata-Version: 2.1
Name: repartee
Version: 0.1.1
Summary: A CLI tool to interface with multiple AI APIs for prompt-response handling.
Home-page: https://github.com/matias-ceau/repartee
Author: Matias Ceau
Author-email: matias@ceau.net
Project-URL: Bug Tracker, https://github.com/matias-ceau/repartee/issues
Project-URL: Source Code, https://github.com/matias-ceau/repartee
Classifier: Programming Language :: Python :: 3
Classifier: License :: OSI Approved :: MIT License
Classifier: Operating System :: OS Independent
Classifier: Development Status :: 3 - Alpha
Classifier: Intended Audience :: Developers
Classifier: Topic :: Software Development :: Libraries :: Python Modules
Requires-Python: >=3.6
License-File: LICENSE
Requires-Dist: requests >=2.25.1
Requires-Dist: PyYAML >=5.4.1
Requires-Dist: prompt-toolkit >=3.0.18
Requires-Dist: setuptools >=58.0.0
Requires-Dist: wheel >=0.36.2
Requires-Dist: twine >=3.4.1
